<?xml version="1.0" encoding="utf-8"?>
<base xmlns:xsi="http://www.w3.org/2001/XMLSchema-instance" xmlns:xsd="http://www.w3.org/2001/XMLSchema" type="string">
<strings>
<!--input/trooptrees/spnpccharacters_Bierbierski.xml-->
<string id="CsjtWt1g" text="Haspadar Karčmy" />
<string id="twCIejxn" text="Majstar Hulniaŭ" />
<string id="zfCoeglY" text="Muzyka" />
<string id="z6RMWTaA" text="Pakajoŭka Karčmy" />
<string id="jx8ohENz" text="Brońnik" />
<string id="79ElOr2x" text="Handlar Końmi" />
<string id="thbcgVVO" text="Handlar" />
<string id="malebeggar" text="Žabrak" />
<string id="femalebeggar" text="Žabračka" />
<string id="X3KYysuv" text="Tancor" />
<string id="IHKXNP9H" text="Zahadnik Turniraŭ" />
<string id="maleinfant" text="Niemaŭlo" />
<string id="malechild" text="Dzicio" />
<string id="maleteenager" text="Padletak" />
<string id="femaleinfant" text="Niemaŭlo" />
<string id="femalechild" text="Dzicio" />
<string id="femaleteenager" text="Padletak" />
<string id="275LD0Gh" text="Pracaŭnik Majsterni" />
<string id="muu5cofb" text="Haradžanin" />
<string id="AlmaRAib" text="Nataryus Zamožnaha Viaskoŭca" />
<string id="bLMGbLF8" text="Nataryus Prapaviednika" />
<string id="ECxiXTbF" text="Nataryus Ramieśnika" />
<string id="reoVAtrE" text="Nataryus Handlara" />
<string id="LNNXiPyV" text="Ciełaachoŭnik Vierchavoda Bandy" />
<string id="W2WXkiAh" text="Pasiarednik-Vykupnik" />
<string id="WH7EGGIg" text="Cyrulnik" />
<string id="UaN2lfwi" text="Zbrojnik" />
<string id="bNnQt4jN" text="Kaval" />
<string id="XgjXfmM1" text="Vartaŭnik Viaźnicy" />
<string id="E11BEt01" text="Bierbierskaja Viaskoŭka" />
<string id="E11BEt02" text="Bierbierski Majstar Karavanaŭ" />
<string id="E11BEt03" text="Bierbierski Uzbrojeny Handlar" />
<string id="E11BEt04" text="Bierbierski Achoŭnik Karavanaŭ" />
<string id="E11BEt05" text="Bierbierski Achoŭnik Karavanaŭ Vieteran" />
<string id="E11BEt06" text="Bierbierski Chušud"/>
<string id="E11BEt07" text="Bierbierski Plamienny Kapijnik"/>
<string id="E11BEt08" text="Bierbierski Mutataŭjia"/>
<string id="E11BEt09" text="Bierbierski Hchazi"/>
<string id="E11BEt10" text="Bierbierski Plamienny Kapijnik-Vieteran"/>
<string id="E11BEt11" text="Bierbierski Murtazika"/>
<string id="E11BEt12" text="Bierbierski Plamienny Łučnik"/>
<string id="E11BEt13" text="Bierbierski Plamienny Łučnik-Vieteran"/>
<string id="E11BEt14" text="Bierbierski Łamtunach-Łučnik "/>
<string id="E11BEt15" text="Bierbierski Mułatamun"/>
<string id="E11BEt16" text="Bierbierski Hranadzin"/>
<string id="E11BEt17" text="Bierbierski Ciažki Hranadzin"/>
<string id="E11CRt1" text="Utrumerskaja Viaskoŭka"/>
<string id="E11CRt2" text="Utrumerski Majstar Karavanaŭ"/>
<string id="E11CRt3" text="Utrumerski Uzbrojeny Handlar"/>
<string id="E11CRt4" text="Utrumerski Achoŭnik Karavanaŭ"/>
<string id="E11CRt5" text="Utrumerski Achoŭnik Karavanaŭ Vieteran"/>
<string id="E11CRt6" text="Utrumerski Pilihrym"/>
<string id="E11CRt7" text="Utrumerski Kapijnik"/>
<string id="E11CRt8" text="Utrumerski Kapijnik Braterstva"/>
<string id="E11CRt9" text="Utrumerski Siaržant-Kapijnik"/>
<string id="E11CRt10" text="Utrumerski Arbaletnik"/>
<string id="E11CRt11" text="Utrumerski Arbaletnik Braterstva"/>
<string id="E11CRt12" text="Utrumerski Arbaletnik-Majstar"/>
<string id="E11CRt13" text="Utrumerski Turkapoli Lohki Vieršnik"/>
<string id="E11CRt14" text="Utrumerski Turkapoli Konny Łučnik"/>
<string id="E11CRt15" text="Utrumerski Špitaljer-Rycar"/>
<string id="E11CRt16" text="Utrumerski Špitaljer-Honfanońjer"/>
<string id="E11CRt17" text="Utrumerski Špitaljer-Maršał"/>
<!--input/trooptrees/spnpccharacters_byzantine.xml-->
<string id="E11BYt01" text="Bizantyjskaja Viaskoŭka" />
<string id="E11BYt02" text="Bizantyjski Majstar Karavanaŭ" />
<string id="E11BYt03" text="Bizantyjski Uzbrojeny Handlar" />
<string id="E11BYt04" text="Bizantyjski Achoŭnik Karavanaŭ" />
<string id="E11BYt05" text="Bizantyjski Achoŭnik Karavanaŭ Vieteran" />
<string id="E11BYt07" text="Bizantyjski Tahma"/>
<string id="E11BYt08" text="Bizantyjski Toksaty"/>
<string id="E11BYt09" text="Bizantyjski Trapezund Toksaty"/>
<string id="E11BYt10" text="Bizantyjski Pałacinny Vartavy"/>
<string id="E11BYt11" text="Bizantyjski Skotaty"/>
<string id="E11BYt12" text="Bizantyjski Menolon"/>
<string id="E11BYt13" text="Bizantyjski Spatary"/>
<string id="E11BYt14" text="Bizantyjski Domeścikas"/>
<string id="E11BYt15" text="Bizantyjski Nomery"/>
<string id="E11BYt16" text="Bizantyjski Archontapoli"/>
<string id="E11BYt17" text="Bizantyjski Atanaty"/>
<string id="E11BYt18" text="Bizantyjski Katafrakty"/>
<!--input/trooptrees/spnpccharacters_cRuśkiade.xml-->
<string id="E11CRt01" text="Pilihrym" />
<string id="E11CRt02" text="Francki Zbrojanos" />
<string id="E11CRt03" text="Francki Rycar-Kryžak" />
<string id="E11CRt04" text="Francki Lehiendarny Kryžak" />
<!--input/trooptrees/spnpccharacters_cumans.xml-->
<string id="kPCcelVX" text="Handlar" />
<string id="E11CUt01" text="Uschodniaja Viaskoŭka" />
<string id="E11CUt02" text="Uschodni Majstar Karavanaŭ" />
<string id="E11CUt03" text="Uschodni Uzbrojeny Handlar" />
<string id="E11CUt04" text="Uschodni Achoŭnik Karavanaŭ" />
<string id="E11CUt05" text="Uschodni Achoŭnik Karavanaŭ Vieteran" />
<string id="E11CUt06" text="Pałaviecki Kačeŭnik"/>
<string id="E11CUt07" text="Pałaviecki Kačeŭnik-Kapijnik"/>
<string id="E11CUt08" text="Pałaviecki Kačeŭnik Vieteran Kapijnik"/>
<string id="E11CUt09" text="Pałaviecki Kačeŭnik Ciełaachoŭnik"/>
<string id="E11CUt10" text="Pałaviecki Kačeŭnik Łučnik"/>
<string id="E11CUt11" text="Pałaviecki Kačeŭnik Vieteran Łučnik"/>
<string id="E11CUt12" text="Pałaviecki Trapny Strałok"/>
<string id="E11CUt13" text="Pałaviecki Konny Łučnik"/>
<string id="E11CUt14" text="Pałaviecki Vieteran Konny Łučnik"/>
<string id="E11CUt15" text="Pałaviecki Lohki Vieršnik"/>
<string id="E11CUt16" text="Pałaviecki Ciažki Vieršnik"/>
<string id="E11CUt17" text="Pałaviecki Vartaŭnik Chana"/>
<!--input/trooptrees/spnpccharacters_english.xml-->
<string id="E11ENt01" text="Anhlijskaja Viaskoŭka" />
<string id="E11ENt02" text="Anhlijski Majstar Karavanaŭ" />
<string id="E11ENt03" text="Anhlijski Uzbrojeny Handlar" />
<string id="E11ENt04" text="Anhlijski Achoŭnik Karavanaŭ" />
<string id="E11ENt05" text="Anhlijski Achoŭnik Karavanaŭ Vieteran" />
<string id="E11ENt06" text="Anhlijski Zakličnik"/>
<string id="E11ENt07" text="Anhlijski Fiord-Kapijnik"/>
<string id="E11ENt08" text="Anhlijski Fiord Vieteran Kapijnik"/>
<string id="E11ENt09" text="Anhlijski Siaržant-Kapijnik"/>
<string id="E11ENt10" text="Anhlijski Fiord-Łučnik"/>
<string id="E11ENt11" text="Anhlijski Fiord Vieteran Łučnik"/>
<string id="E11ENt12" text="Anhlijski Siaržant-Łučnik"/>
<string id="E11ENt13" text="Anhlijski Siakirnik"/>
<string id="E11ENt14" text="Anhlijski Siaržant-Siakirnik"/>
<string id="E11ENt15" text="Anhlijski Zbrojanos"/>
<string id="E11ENt16" text="Anhlijski Jomen"/>
<string id="E11ENt17" text="Anhlijski Rycar"/>
<!--input/trooptrees/spnpccharacters_fatimid.xml-->
<string id="E11FAt01" text="Arabskaja Viaskoŭka" />
<string id="E11FAt02" text="Arabski Majstar Karavanaŭ" />
<string id="E11FAt03" text="Arabski Uzbrojeny Handlar" />
<string id="E11FAt04" text="Arabski Achoŭnik Karavanaŭ" />
<string id="E11FAt05" text="Arabski Achoŭnik Karavanaŭ Vieteran" />
<string id="E11FAt06" text="Facimidzki Zakličnik"/>
<string id="E11FAt07" text="Facimidzki Kapijnik Rušeńnia"/>
<string id="E11FAt08" text="Facimidzki Kapijnik-Vieteran Rušeńnia"/>
<string id="E11FAt09" text="Facimidzki Hchazi-Miečnik"/>
<string id="E11FAt10" text="Facimidzki Łučnik Rušeńnia"/>
<string id="E11FAt11" text="Facimidzki Łučnik-Vieteran Rušeńnia"/>
<string id="E11FAt12" text="Facimidzki Hchazi-Łučnik"/>
<string id="E11FAt13" text="Facimidzki Bieduin Konny Łučnik"/>
<string id="E11FAt14" text="Facimidzki Bieduin Konny Łučnik-Vieteran"/>
<string id="E11FAt15" text="Facimidzki Mamluk"/>
<string id="E11FAt16" text="Facimidzki Mamluk-Vieteran"/>
<string id="E11FAt17" text="Facimidzkaja Chudžaryja"/>
<!--input/trooptrees/spnpccharacters_france.xml-->
<string id="E11FRt01" text="Franckaja Viaskoŭka" />
<string id="E11FRt02" text="Francki Majstar Karavanaŭ" />
<string id="E11FRt03" text="Francki Uzbrojeny Handlar" />
<string id="E11FRt04" text="Francki Achoŭnik Karavanaŭ" />
<string id="E11FRt05" text="Francki Achoŭnik Karavanaŭ Vieteran" />
<string id="E11FRt07" text="Francki Zakličnik"/>
<string id="E11FRt08" text="Francki Kapijnik Rušeńnia"/>
<string id="E11FRt09" text="Francki Kapijnik-Vieteran Rušeńnia"/>
<string id="E11FRt10" text="Francki Siaržant Kapijnik"/>
<string id="E11FRt11" text="Francki Arbaletnik Rušeńnia"/>
<string id="E11FRt12" text="Francki Arbaletnik-Vieteran Rušeńnia"/>
<string id="E11FRt13" text="Francki Arbaletnik-Majstar"/>
<string id="E11FRt14" text="Francki Zbrojny Čyn"/>
<string id="E11FRt15" text="Francki Zbrojny Čyn Siaržant"/>
<string id="E11FRt16" text="Francki Zbrojanos"/>
<string id="E11FRt17" text="Francki Rycar Ściaha"/>
<string id="E11FRt18" text="Francki Maršał"/>
<!--input/trooptrees/spnpccharacters_germany.xml-->
<string id="E11GEt01" text="Hiermanskaja Viaskoŭka" />
<string id="E11GEt02" text="Hiermanski Majstar Karavanaŭ" />
<string id="E11GEt03" text="Hiermanski Uzbrojeny Handlar" />
<string id="E11GEt04" text="Hiermanski Achoŭnik Karavanaŭ" />
<string id="E11GEt05" text="Hiermanski Achoŭnik Karavanaŭ Vieteran" />
<string id="E11GEt07" text="Hiermanski Chierrbann"/>
<string id="E11GEt08" text="Hiermanski Kapijnik Rušeńnia"/>
<string id="E11GEt09" text="Hiermanski Kapijnik-Vieteran Rušeńnia"/>
<string id="E11GEt10" text="Hiermanski Siaržant-Kapijnik"/>
<string id="E11GEt11" text="Hiermanski Arbaletnik Rušeńnia"/>
<string id="E11GEt12" text="Hiermanski Arbaletnik-Vieteran Rušeńnia"/>
<string id="E11GEt13" text="Hiermanski Siaržant-Arbaletnik"/>
<string id="E11GEt14" text="Hiermanski Švabski Miečnik"/>
<string id="E11GEt15" text="Hiermanski Konny Švabski Miečnik"/>
<string id="E11GEt16" text="Hiermanski Konny Siaržant"/>
<string id="E11GEt17" text="Hiermanski Dzinštłajnten"/>
<string id="E11GEt18" text="Hiermanski Šlachietny Rycar"/>
<!--input/trooptrees/spnpccharacters_hungary.xml-->
<string id="E11HUt01" text="Vuhorskaja Viaskoŭka" />
<string id="E11HUt02" text="Vuhorski Majstar Karavanaŭ" />
<string id="E11HUt03" text="Vuhorski Uzbrojeny Handlar" />
<string id="E11HUt04" text="Vuhorski Achoŭnik Karavanaŭ" />
<string id="E11HUt05" text="Vuhorski Achoŭnik Karavanaŭ Vieteran" />
<string id="E11HUt07" text="Vuhorski Zakličnik"/>
<string id="E11HUt08" text="Vuhorski Kapijnik Rušeńnia"/>
<string id="E11HUt09" text="Vuhorski Kapijnik-Vieteran Rušeńnia"/>
<string id="E11HUt10" text="Vuhorski Jobadžyanis-Piachotnik"/>
<string id="E11HUt11" text="Vuhorski Łučnik Rušeńnia"/>
<string id="E11HUt12" text="Vuhorski Łučnik-Vieteran Rušeńnia"/>
<string id="E11HUt13" text="Vuhorski Jobadžyanis-Łučnik"/>
<string id="E11HUt14" text="Vuhorski Konny Łučnik"/>
<string id="E11HUt15" text="Vuhorski Konny Łučnik Vieteran"/>
<string id="E11HUt16" text="Vuhorski Ban"/>
<string id="E11HUt17" text="Vuhorski Išpan"/>
<string id="E11HUt18" text="Vuhorski Nadoryšpan"/>
<!--input/trooptrees/spnpccharacters_irish.xml-->
<string id="E11IRt01" text="Irłandzkaja Viaskoŭka" />
<string id="E11IRt02" text="Irłandzki Majstar Karavanaŭ" />
<string id="E11IRt03" text="Irłandzki Uzbrojeny Handlar" />
<string id="E11IRt04" text="Irłandzki Achoŭnik Karavanaŭ" />
<string id="E11IRt05" text="Irłandzki Achoŭnik Karavanaŭ Vieteran" />
<string id="E11IRt06" text="Irłandzki Zakličnik"/>
<string id="E11IRt07" text="Irłandzki Kapijnik Rušeńnia"/>
<string id="E11IRt08" text="Irłandzki Kapijnik-Vieteran Rušeńnia"/>
<string id="E11IRt09" text="Irłandzki Siakirnik"/>
<string id="E11IRt10" text="Irłandzki Łučnik Rušeńnia"/>
<string id="E11IRt11" text="Irłandzki Łučnik-Vieteran Rušeńnia"/>
<string id="E11IRt12" text="Irłandzki Sajhchdeojry"/>
<string id="E11IRt13" text="Irłandzki Zastrelnik"/>
<string id="E11IRt14" text="Irłandzki Vyviednik"/>
<string id="E11IRt15" text="Irłandzki Kiern"/>
<string id="E11IRt16" text="Irłandzki Ostmen"/>
<string id="E11IRt17" text="Irłandzki Hałłohłajch"/>
<!--input/trooptrees/spnpccharacters_italy.xml-->
<string id="E11ITt01" text="Italjanskaja Viaskoŭka" />
<string id="E11ITt02" text="Italjanski Majstar Karavanaŭ" />
<string id="E11ITt03" text="Italjanski Uzbrojeny Handlar" />
<string id="E11ITt04" text="Italjanski Achoŭnik Karavanaŭ" />
<string id="E11ITt05" text="Italjanski Achoŭnik Karavanaŭ" />
<string id="E11ITt07" text="Italjanski Zakličnik"/>
<string id="E11ITt08" text="Italjanski Kontadzini-Kapijnik"/>
<string id="E11ITt09" text="Italjanski Kontadzini-Kapijnik Vieteran"/>
<string id="E11ITt10" text="Italjanski Kapitani-Pikinior"/>
<string id="E11ITt11" text="Italjanski Kontadzini-Arbaletnik"/>
<string id="E11ITt12" text="Italjanski Kontadzini-Arbaletnik Vieteran"/>
<string id="E11ITt13" text="Italjanski Kapitani-Arbaletnik"/>
<string id="E11ITt14" text="Italjanski Kontadzini-Vieršnik"/>
<string id="E11ITt15" text="Italjanski Kontadzini-Vieršnik Vieteran"/>
<string id="E11ITt16" text="Italjanski Šlachietny Kommjune"/>
<string id="E11ITt17" text="Italjanski Milites Pro Kommjune"/>
<string id="E11ITt18" text="Italjanski Vavassores"/>
<!--input/trooptrees/spnpccharacters_mercs.xml-->
<string id="E11ARMENIAN_tr1" text="Armianski Kapijnik" />
<string id="E11ARMENIAN_tr2" text="Armianski Zastrelnik" />
<string id="E11ARMENIAN_tr3" text="Armianski Ciažki Vieršnik" />
<string id="E11ST_MICHAEL_tr1" text="Rycar Śviatoha Michaiła" />
<string id="E11ST_MICHAEL_tr2" text="Kamandar Śviatoha Michaiła" />
<string id="E11ST_MICHAEL_tr3" text="Hrand Aficer Śviatoha Michaiła" />
<string id="E11PECHENEGS_tr1" text="Kipčaski Konny Łučnik" />
<string id="E11PECHENEGS_tr2" text="Kipčaski Konny Łučnik Vieteran" />
<string id="E11PECHENEGS_tr3" text="Kipčaski Vartaŭnik Chana" />
<string id="E11LAZARUS_tr1" text="Pizanski Matros" />
<string id="E11LAZARUS_tr2" text="Pizanski Marak" />
<string id="E11LAZARUS_tr3" text="Pizanski Rycar" />
<string id="E11ASSASINS_tr1" text="Asasin-Inicyjant" />
<string id="E11ASSASINS_tr2" text="Asasin-Paśladoŭnik" />
<string id="E11ASSASINS_tr3" text="Asasin-Majstar" />
<string id="E11POWYS_tr1" text="Małady Voŭk" />
<string id="E11POWYS_tr2" text="Daśviedčany Voŭk" />
<string id="E11POWYS_tr3" text="Abrany Voŭk" />
<string id="E11GENOESE_tr1" text="Hienueski Marak" />
<string id="E11GENOESE_tr2" text="Hienueski Arbaletnik" />
<string id="E11GENOESE_tr3" text="Hienueski Arbaletnik-Vieteran" />
<string id="E11VARAG_tr1" text="Varah" />
<string id="E11VARAG_tr2" text="Varah-Najmit" />
<string id="E11VARAG_tr3" text="Varah-Ciełaachoŭnik" />
<string id="E11HOSPITAL_tr1" text="Pruski Ukininkas" />
<string id="E11HOSPITAL_tr2" text="Pruski Bajaras" />
<string id="E11HOSPITAL_tr3" text="Pruski Rykis" />
<string id="E11GEORG_tr1" text="Hruzinski Aznaury" />
<string id="E11GEORG_tr2" text="Hruzinski Erystavi" />
<string id="E11GEORG_tr3" text="Hruzinski Tavadzi" />
<string id="E11DANISHMENDS_tr1" text="Danišmendzki Konny Łučnik" />
<string id="E11DANISHMENDS_tr2" text="Danišmendzki Konny Łučnik Vieteran" />
<string id="E11DANISHMENDS_tr3" text="Danišmendzki Konny Łučnik Čempijon" />
<string id="E11PECHENEGS_tr1" text="Piečanieski Konny Łučnik" />
<string id="E11PECHENEGS_tr2" text="Piečanieski Konny Łučnik Vieteran" />
<string id="E11PECHENEGS_tr3" text="Piečanieski Vartaŭnik Chana" />
<string id="E11GWYNEDD_tr1" text="Ŭelski Kapijnik" />
<string id="E11GWYNEDD_tr2" text="Ŭelski Cieułu" />
<string id="E11GWYNEDD_tr3" text="Ŭelski Uchielvar" />
<string id="E11JAMES_tr1" text="Parafijanin Śviatoha Jakava" />
<string id="E11JAMES_tr2" text="Brat Śviatoha Jakava" />
<string id="E11JAMES_tr3" text="Rycar Śviatoha Jakava" />
<string id="E11TAVERN_tr1" text="Najmit-Sałdat"/>
<string id="E11TAVERN_tr2" text="Najmit-Kaprał"/>
<string id="E11TAVERN_tr3" text="Najmit-Siaržant"/>
<string id="E11TAVERN_tr4" text="Najmit-Rycar"/>
<string id="E11TAVERN_tr5" text="Najmit-Złodziej"/>
<string id="E11TAVERN_tr6" text="Najmit-Ašukaniec"/>
<string id="E11TAVERN_tr7" text="Najmit Ašukaniec Vieteran"/>
<string id="E11TAVERN_tr8" text="Najmit Konny Łučnik"/>
<string id="E11TAVERN_tr9" text="Najmit Konny Łučnik Vieteran"/>
<string id="E11TAVERN_tr10" text="Najmit-Vikinh"/>
<string id="E11TAVERN_tr11" text="Najmit Vikinh Vieteran"/>
<string id="E11TAVERN_tr12" text="Najmit-Chaŭskarł"/>
<string id="E11TAVERN_tr13" text="Najmit-Śledapyt"/>
<string id="E11TAVERN_tr14" text="Najmit Śledapyt Vieteran"/>
<string id="r8npO8hG" text="Najmit-Sałdat"/>
<string id="ZK0GXYCx" text="Najmit-Kaprał"/>
<string id="ifL3F7E2" text="Najmit-Siaržant"/>
<string id="0gi5Fp8c" text="Najmit-Rycar"/>
<string id="NRvuCvMN" text="Najmit-Złodziej"/>
<string id="UBHngTIf" text="Najmit-Ašukaniec"/>
<string id="uPypJHlm" text="Najmit-Ašukaniec Vieteran"/>
<string id="xl6QstMW" text="Najmit Konny Łučnik"/>
<string id="kyt087eN" text="Najmit Konny Łučnik Vieteran"/>
<string id="J4k9mg65" text="Najmit-Vikinh"/>
<string id="n89z19Dv" text="Najmit-Vikinh Vieteran"/>
<string id="7WV17e5Q" text="Najmit-Chuskarł"/>
<string id="QfVe3IVw" text="Najmit-Sledapyt"/>
<string id="DxtSIxyZ" text="Najmit-Sledapyt Vieteran"/>
<string id="E11NOt01" text="Nardyčnaja Viaskoŭka" />
<string id="E11NOt02" text="Nardyčny Majstar Karavanaŭ" />
<string id="E11NOt03" text="Nardyčny Uzbrojeny Handlar" />
<string id="E11NOt04" text="Nardyčny Achoŭnik Karavanaŭ" />
<string id="E11NOt05" text="Nardyčny Achoŭnik Karavanaŭ Vieteran" />
<string id="E11NOt06" text="Nardyčny Karł"/>
<string id="E11NOt07" text="Nardyčny Łajjanhr-Kapijnik"/>
<string id="E11NOt08" text="Nardyčny Łajjanhr-Kapijnik Vieteran"/>
<string id="E11NOt09" text="Nardyčny Chuskarł"/>
<string id="E11NOt10" text="Nardyčny Łajjanhr-Łučnik"/>
<string id="E11NOt11" text="Nardyčny Łajjanhr-Łučnik Vieteran"/>
<string id="E11NOt12" text="Nardyčny Mierkismer"/>
<string id="E11NOt13" text="Nardyčny Biersierkier"/>
<string id="E11NOt14" text="Nardyčny Ulfednar"/>
<string id="E11NOt15" text="Nardyčny Kiercisvajner"/>
<string id="E11NOt16" text="Nardyčny Hieścir"/>
<string id="E11NOt17" text="Nardyčny Chirdmenn"/>
<string id="E11PEt01" text="Sieldžuskaja Viaskoŭka" />
<string id="E11PEt02" text="Sieldžuski Majstar Karavanaŭ" />
<string id="E11PEt03" text="Sieldžuski Uzbrojeny Handlar" />
<string id="E11PEt04" text="Sieldžuski Achoŭnik Karavanaŭ" />
<string id="E11PEt05" text="Sieldžuski Achoŭnik Karavanaŭ Vieteran" />
<string id="E11PEt06" text="Sieldžuski Turkmenn"/>
<string id="E11PEt07" text="Sieldžuski Plamienny Kapijnik"/>
<string id="E11PEt08" text="Sieldžuski Plamienny Kapijnik-Vieteran"/>
<string id="E11PEt09" text="Sieldžuski Plamienny Lohki Vieršnik"/>
<string id="E11PEt10" text="Sieldžuski Plamienny Łučnik"/>
<string id="E11PEt11" text="Sieldžuski Plamienny Łučnik-Vieteran"/>
<string id="E11PEt12" text="Sieldžuski Plamienny Zastrelnik"/>
<string id="E11PEt13" text="Sieldžuski Konny Łučnik"/>
<string id="E11PEt14" text="Sieldžuski Konny Łučnik Vieteran"/>
<string id="E11PEt15" text="Sieldžuski Hchułam Lohki Vieršnik"/>
<string id="E11PEt16" text="Sieldžuski Hchułam Ciažki Vieršnik"/>
<string id="E11PEt17" text="Sieldžuski Hchułam Askary"/>
<string id="E11POt01" text="Polskaja Viaskoŭka" />
<string id="E11POt02" text="Polski Majstar Karavanaŭ" />
<string id="E11POt03" text="Polski Uzbrojeny Handlar" />
<string id="E11POt04" text="Polski Achoŭnik Karavanaŭ" />
<string id="E11POt05" text="Polski Achoŭnik Karavanaŭ Vieteran" />
<string id="E11POt07" text="Polski Zakličnik"/>
<string id="E11POt08" text="Polski Siakirnik Rušeńnia"/>
<string id="E11POt09" text="Polski Siakirnik-Vieteran Rušeńnia"/>
<string id="E11POt10" text="Polski Vłodyka-Piachotnik"/>
<string id="E11POt11" text="Polski Łučnik Rušeńnia"/>
<string id="E11POt12" text="Polski Łučnik-Vieteran Rušeńnia"/>
<string id="E11POt13" text="Polski Vłodyka-Łučnik"/>
<string id="E11POt14" text="Polski Tarčoŭnicy"/>
<string id="E11POt15" text="Polski Tarčoŭnicy-Vieteran"/>
<string id="E11POt16" text="Polski Družyńnik"/>
<string id="E11POt17" text="Polski Šlachcič"/>
<string id="E11POt18s" text="Polski Rycerž"/>
<string id="E11SCt01" text="Šatłandzkaja Viaskoŭka" />
<string id="E11SCt02" text="Šatłandzki Majstar Karavanaŭ" />
<string id="E11SCt03" text="Šatłandzki Uzbrojeny Handlar" />
<string id="E11SCt04" text="Šatłandzki Achoŭnik Karavanaŭ" />
<string id="E11SCt05" text="Šatłandzki Achoŭnik Karavanaŭ Vieteran" />
<string id="E11SCt06" text="Šatłandzki Nejf"/>
<string id="E11SCt07" text="Šatłandzki Kapijnik Rušeńnia"/>
<string id="E11SCt08" text="Šatłandzki Kapijnik-Vieteran Rušeńnia"/>
<string id="E11SCt09" text="Šatłandzki Horny Kapijnik"/>
<string id="E11SCt10" text="Šatłandzki Łučnik Rušeńnia"/>
<string id="E11SCt11" text="Šatłandzki Łučnik-Vieteran Rušeńnia"/>
<string id="E11SCt12" text="Šatłandzki Horny Łučnik"/>
<string id="E11SCt13" text="Šatłandzki Miečnik"/>
<string id="E11SCt14" text="Šatłandzki Horny Miečnik"/>
<string id="E11SCt15" text="Šatłandzki Lohki Vieršnik"/>
<string id="E11SCt16" text="Šatłandzki Rycar"/>
<string id="E11SCt17" text="Šatłandzki Rycar-Čempijon"/>
<string id="E11SIt1" text="Sicylijskaja Viaskoŭka"/>
<string id="E11SIt2" text="Sicylijski Majstar Karavanaŭ"/>
<string id="E11SIt3" text="Sicylijski Uzbrojeny Handlar"/>
<string id="E11SIt4" text="Sicylijski Achoŭnik Karavanaŭ"/>
<string id="E11SIt5" text="Sicylijski Achoŭnik Karavanaŭ Vieteran"/>
<string id="E11SIt6" text="Sicylijski Zakličnik"/>
<string id="E11SIt7" text="Sicylijski Kapijnik Rušeńnia"/>
<string id="E11SIt8" text="Sicylijski Kapijnik-Vieteran Rušeńnia "/>
<string id="E11SIt9" text="Sicylijski Siaržant-Kapijnik"/>
<string id="E11SIt10" text="Sicylijski Łučnik Rušeńnia"/>
<string id="E11SIt11" text="Sicylijski Łučnik-Vieteran Rušeńnia"/>
<string id="E11SIt12" text="Sicylijski Siaržant-Łučnik"/>
<string id="E11SIt13" text="Sicylijski Zbrojny Čyn"/>
<string id="E11SIt14" text="Sicylijski Lohki Vieršnik"/>
<string id="E11SIt15" text="Sicyła-Narmanski Zbrojanos"/>
<string id="E11SIt16" text="Sicyła-Narmanski Rycar"/>
<string id="E11SIt17" text="Sicyła-Narmanski Maršał"/>
<string id="E11RUt01" text="Ruśki Majstar Karavanaŭ"/>
<string id="E11RUt02" text="Ruśki Uzbrojeny Handlar"/>
<string id="E11RUt03" text="Ruśki Achoŭnik Karavanaŭ Vieteran"/>
<string id="E11RUt04" text="Ruśki Achoŭnik Karavanaŭ"/>
<string id="E11RUt06" text="Ruśki Śmierd"/>
<string id="E11RUt07" text="Ruśki Voj-Kapijnik"/>
<string id="E11RUt08" text="Ruśki Voj-Kapijnik Vieteran"/>
<string id="E11RUt09" text="Ruśki Pałkavy-Siakirnik"/>
<string id="E11RUt10" text="Ruśki Voj-Łučnik"/>
<string id="E11RUt11" text="Ruśki Voj-Łučnik Vieteran"/>
<string id="E11RUt12" text="Ruśki Pałkavy-Łučnik"/>
<string id="E11RUt13" text="Ruśki Dziecki"/>
<string id="E11RUt14" text="Ruśki Otrok"/>
<string id="E11RUt15" text="Ruśki Bajavy Chałop"/>
<string id="E11RUt16" text="Ruśki Hrydź"/>
<string id="E11RUt17" text="Ruśki Socienny"/>
<string id="E11SPt01" text="Hišpanskaja Viaskoŭka" />
<string id="E11SPt02" text="Hišpanski Majstar Karavanaŭ" />
<string id="E11SPt03" text="Hišpanski Uzbrojeny Handlar" />
<string id="E11SPt04" text="Hišpanski Achoŭnik Karavanaŭ" />
<string id="E11SPt05" text="Hišpanski Achoŭnik Karavanaŭ Vieteran" />
<string id="E11SPt07" text="Hišpanski Pionis"/>
<string id="E11SPt08" text="Hišpanski Kapijnik Rušeńnia"/>
<string id="E11SPt09" text="Hišpanski Kapijnik-Vieteran Rušeńnia"/>
<string id="E11SPt10" text="Hišpanski Bidet"/>
<string id="E11SPt11" text="Hišpanski Arbaletnik Rušeńnia"/>
<string id="E11SPt12" text="Hišpanski Arbaletnik-Vieteran Rušeńnia"/>
<string id="E11SPt13" text="Hišpanski Ballestera"/>
<string id="E11SPt14" text="Hišpanski Lohki Vieršnik"/>
<string id="E11SPt15" text="Hišpanski Džynit"/>
<string id="E11SPt16" text="Hišpanski Tałajeros"/>
<string id="E11SPt17" text="Hišpanski Kaballeros"/>
<string id="E11SPt18" text="Hišpanski Šlachietny Kaballeros"/>
</strings>
</base>