<?xml version="1.0" encoding="utf-8"?>
<base xmlns:xsi="http://www.w3.org/2001/XMLSchema-instance" xmlns:xsd="http://www.w3.org/2001/XMLSchema" type="string">
    <strings>
        <string id="XuxARPTM" text="{HERO.FIRSTNAME} Bitterdraught " />
        <string id="ntkipfCV" text="{HERO.FIRSTNAME} the Loud " />
        <string id="7lg12a57" text="{HERO.FIRSTNAME} the Brave " />
        <string id="ZCc3VFat" text="{HERO.FIRSTNAME} the Grizzled " />
        <string id="8o5SDCCJ" text="{HERO.FIRSTNAME} the Shark " />
        <string id="WvwWX4me" text="{HERO.FIRSTNAME} Barrelchest " />
        <string id="OArAImbM" text="{HERO.FIRSTNAME} of the Hills " />
        <string id="c5Kjcxsa" text="{HERO.FIRSTNAME} the Huntress " />
        <string id="hrMatilh" text="{HERO.FIRSTNAME} the Smith " />
        <string id="7apnGFz7" text="{HERO.FIRSTNAME} the Black " />
        <string id="6CAbkgS4" text="{HERO.FIRSTNAME} the Wainwright " />
        <string id="nDtjEazo" text="{HERO.FIRSTNAME} Deadeye " />
        <string id="QGcgQDqK" text="{HERO.FIRSTNAME} the Tracker " />
        <string id="!" text="Rhodok Rebellion Leader " />
        <string id="npc.tournament_master_rhodok" text="Tournament Master " />
        <string id="npc.prison_guard_rhodok" text="Prison Guard " />
        <string id="npc.guard_rhodok" text="Guard " />
        <string id="npc.blacksmith_rhodok" text="Blacksmith " />
        <string id="npc.weaponsmith_rhodok" text="Weaponsmith " />
        <string id="npc.townswoman_infant_rhodok" text="Infant " />
        <string id="npc.townswoman_child_rhodok" text="Child " />
        <string id="npc.townswoman_teenager_rhodok" text="Teenager " />
        <string id="npc.townsman_infant_rhodok" text="Infant " />
        <string id="npc.townsman_child_rhodok" text="Child " />
        <string id="npc.townsman_teenager_rhodok" text="Teenager " />
        <string id="npc.townsman_rhodok" text="Townsman " />
        <string id="npc.ransom_broker_rhodok" text="Ransom Broker " />
        <string id="npc.gangleader_bodyguard_rhodok" text="Gang Leader Bodyguard " />
        <string id="npc.merchant_notary_rhodok" text="Merchant Notary " />
        <string id="npc.artisan_notary_rhodok" text="Artisan Notary " />
        <string id="npc.preacher_notary_rhodok" text="Preacher Notary " />
        <string id="npc.rural_notable_notary_rhodok" text="Rural Notable Notary " />
        <string id="npc.shop_worker_rhodok" text="Shop Worker " />
        <string id="npc.tavernkeeper_rhodok" text="Tavern Keeper " />
        <string id="npc.taverngamehost_rhodok" text="Game Host " />
        <string id="npc.musician_rhodok" text="Musician " />
        <string id="npc.tavern_wench_rhodok" text="Tavern Maid " />
        <string id="npc.armorer_rhodok" text="Armorer " />
        <string id="npc.horseMerchant_rhodok" text="Horse Trader " />
        <string id="npc.merchant_rhodok" text="Trader " />
        <string id="npc.beggar_rhodok" text="Beggar " />
        <string id="npc.female_beggar_rhodok" text="Beggar " />
        <string id="npc.female_dancer_rhodok" text="Dancer " />
        <string id="npc.gear_practice_dummy_rhodok" text="Rhodok Gear Dummy " />
        <string id="npc.weapon_practice_stage_1_rhodok" text="Rhodok Weapon Dummy " />
        <string id="npc.weapon_practice_stage_2_rhodok" text="Rhodok Weapon Dummy " />
        <string id="npc.weapon_practice_stage_3_rhodok" text="Rhodok Weapon Dummy " />
        <string id="npc.villager_infant_rhodok" text="Infant " />
        <string id="npc.villager_child_rhodok" text="Child " />
        <string id="npc.villager_teenager_rhodok" text="Teenager " />
        <string id="npc.village_woman_infant_rhodok" text="Infant " />
        <string id="npc.village_woman_child_rhodok" text="Child " />
        <string id="npc.village_woman_teenager_rhodok" text="Teenager " />
        <string id="npc.village_woman_rhodok" text="Rhodok Peasant " />
        <string id="npc.barber_rhodok" text="Barber " />
        <string id="npc.rhodok_duel_preset" text="Rhodok Tribesman " />
        <string id="npc.villager_rhodok" text="Rhodok Peasant " />
        <string id="npc.townswoman_rhodok" text="Rhodok Townswoman " />
        <string id="npc.caravan_leader_rhodok" text="Rhodok Mercenaries Leader " />
    </strings>
</base>