<?xml version="1.0" encoding="utf-8"?>
<base xmlns:xsi="http://www.w3.org/2001/XMLSchema-instance" xmlns:xsd="http://www.w3.org/2001/XMLSchema" type="string">
    <strings>
        <string id="str_tor_empire_villager" text="Impierski Viaskoviec " />
        <string id="str_tor_empire_recruit" text="Impierski Rekrut " />
        <string id="str_tor_empire_state_troop" text="Impierski Dziaržaŭny Žaŭnier " />
        <string id="str_tor_empire_swordsman" text="Impierski Miečnik " />
        <string id="str_tor_empire_spearman" text="Impierski Kapijnik " />
        <string id="str_tor_empire_armored_spearman" text="Impierski Braniavany Kapijnik " />
        <string id="str_tor_empire_veteran_swordsman" text="Impierski Miečnik-Vieteran " />
        <string id="str_tor_empire_halberdier" text="Impierski Alebardzir " />
        <string id="str_tor_empire_greatsword" text="Impierski Vydatny Mieč " />
        <string id="str_tor_empire_pikeman" text="Impierski Pikinior " />
        <string id="str_tor_empire_sergeant" text="Impierski Siaržant " />
        <string id="str_tor_empire_scout" text="Impierski Vyviednik " />
        <string id="str_tor_empire_archer" text="Impierski Łučnik " />
        <string id="str_tor_empire_skirmisher" text="Impierski Zastrelnik " />
        <string id="str_tor_empire_handgunner" text="Impierski Strałok " />
        <string id="str_tor_empire_crossbowman" text="Impierski Arbaletnik " />
        <string id="str_tor_empire_longbowman" text="Impierski Dlinnałučnik " />
        <string id="str_tor_empire_huntsman" text="Impierski Palaŭničy " />
        <string id="str_tor_empire_marksman_crossbowman" text="Impierski Arbaletnik-Snajpier " />
        <string id="str_tor_empire_marksman_handgunner" text="Impierski Strałok-Snajpier " />
        <string id="str_tor_empire_young_noble_squire" text="Impierski Małady Šlachietny Zbrojanos " />
        <string id="str_tor_empire_noble_cavalry" text="Impierski Šlachietny Vieršnik " />
        <string id="str_tor_empire_reiksguard_knight" text="Impierski Rajkshardzki Rycar " />
        <string id="str_tor_empire_pistolier" text="Impierski Pistaljer " />
        <string id="str_tor_empire_outrider" text="Impierski Miežavy Najeźnik " />
        <string id="str_tor_empire_reiksguard_preceptor" text="Impierski Rajkshardzki Rycar-Pryseptar " />
        <string id="str_tor_empire_innercircle_knight" text="Impierski Rycar Unutranaha Koła " />
        <string id="str_tor_demigryph_knight" text="Impierski Rycar na Demihryfie " />
        <string id="str_tor_valiant_outrider" text="Impierski Advažny Miežavy Najeźnik " />
        <string id="str_tor_valiant_outrider_grenade" text="Impierski Advažny Miežavy Najeźnik (Hranatakid) " />
        <string id="str_tor_reiksguard_preceptor_innercircle" text="Impierski Rajkshardzki Rycar-Pryseptar Unutranaha Koła " />
        <string id="str_tor_demigryph_innercircle" text="Impierski Rajkshardzki Demihryf Unutranaha Koła " />
        <string id="str_tor_empire_novice_engineer" text="Inžynier-Navik " />
        <string id="str_tor_empire_trainee_artillery_crew" text="Harmatnik-Navik " />
        <string id="str_tor_empire_apprentice_engineer" text="Inžynier-Patužnik " />
        <string id="str_tor_empire_iron_company_guard" text="Vartaŭnik Žaleznaj Kampanii " />
        <string id="str_tor_empire_experienced_artillery_crew" text="Daśviedčany Harmatnik " />
        <string id="str_tor_empire_associate_engineer" text="Inžynier-Vučań " />
        <string id="str_tor_empire_iron_company_troop" text="Žaŭnier Žaleznaj Kampanii " />
        <string id="str_tor_empire_veteran_artillery_crew" text="Harmatnik-Vieteran " />
        <string id="str_tor_empire_master_engineer" text="Inžynier-Majstar " />
        <string id="str_tor_empire_ironsider" text="Nulnski Žaleznaboki " />
        <string id="str_tor_empire_caravan_captain" text="Impierski Kapitan Karavana " />
        <string id="str_tor_empire_caravan_guard" text="Impierski Vartaŭnik Karavana " />
        <string id="str_tor_empire_caravan_vetguard" text="Impierski Rycar " />
        <string id="str_tor_empire_caravan_ranged" text="Impierski Arbaletnik " />
        <string id="str_tor_vc_villager" text="Silvanski Pryhonny " />
        <string id="str_tor_vc_empire_recruit" text="Silvanski Ŭzbrojeny Pryhonny " />
        <string id="str_tor_vc_empire_levy" text="Silvanski Rušeniec " />
        <string id="str_tor_vc_empire_state_troop" text="Silvanski Dziaržaŭny Žaŭnier " />
        <string id="str_tor_vc_empire_veteran_state_troop" text="Silvanski Dziaržaŭny Žaŭnier-Vieteran " />
        <string id="str_tor_vc_empire_sergeant" text="Silvanski Siaržant " />
        <string id="str_tor_vc_empire_archer" text="Silvanski Vyviednik " />
        <string id="str_tor_vc_empire_hunter" text="Silvanski Palaŭničy " />
        <string id="str_tor_vc_empire_ranger" text="Silvanski Rejndžar Bahnaŭ " />
        <string id="str_tor_vc_summoned_skeleton" text="Zaklikany Kaściak " />
        <string id="str_tor_vc_skeleton" text="Kaściak " />
        <string id="str_tor_vc_skeleton_swordsman" text="Kaściak-Miečnik " />
        <string id="str_tor_vc_skeleton_spearman" text="Kaściak-Kapijnik " />
        <string id="str_tor_vc_skeleton_champion" text="Kaściak-Čempijon " />
        <string id="str_tor_vc_skeleton_crypt_guard" text="Vartaŭnik Sklepa " />
        <string id="str_tor_vc_spirit_host" text="Duch-Chost " />
        <string id="str_tor_vc_grave_guard" text="Vartaŭnik Mahiłaŭ " />
        <string id="str_tor_vc_grave_guard_seneschal" text="Vartaŭnik-Sieniešal Mahiłaŭ " />
        <string id="str_tor_vc_cairn_wraith" text="Pryvid Piramidaŭ " />
        <string id="str_tor_vc_crypt_wraith" text="Pryvid Sklepa " />
        <string id="str_tor_vc_drakenhof_guard" text="Drakienchofski Vartaŭnik " />
        <string id="str_tor_vc_hex_wraith" text="Pryvid Nahavoru " />
        <string id="str_tor_vc_black_knight" text="Čorny Rycar " />
        <string id="str_tor_vc_hell_knight" text="Piakielny Rycar " />
        <string id="str_tor_vc_hell_wraith" text="Piakielny Pryvid " />
        <string id="str_tor_vc_vampire_newblood" text="Vampir Novaja Kroŭ " />
        <string id="str_tor_vc_von_carstein" text="Vampir fon Karštajna " />
        <string id="str_tor_vc_von_carstein_sister" text="Siastra fon Karštajna " />
        <string id="str_tor_vc_blood_knight" text="Kryvavy Rycar " />
        <string id="str_tor_vc_von_carstein_noblewoman" text="Šlachcianka fon Karštajna " />
        <string id="str_tor_vc_drakenhof_templar" text="Drakienchofski Tamplijer " />
        <string id="str_tor_vc_von_carstein_countess" text="Hrafinia fon Karštajna " />
        <string id="str_tor_vc_drakenhof_kastelan" text="Drakienchofski Kašcielan " />
        <string id="str_tor_vc_caravan_captain" text="Silvanski Kapitan Karavana " />
        <string id="str_tor_vc_caravan_guard" text="Karavana Vartaŭnik-Vieršnik " />
        <string id="str_tor_vc_caravan_ranged" text="Silvanski Arbaletnik " />
        <string id="str_tor_chaos_nurgle_warrior" text="Hniły Karol Zaniapadu " />
        <string id="str_tor_chaos_nurgle_warrior_002" text="Vajar Nurhła " />
        <string id="str_tor_chaos_nurgle_warrior_003" text="Abrany Nurhła " />
        <string id="str_tor_chaos_chosen" text="Abrany Chaosu " />
        <string id="str_tor_chaos_khorne_warrior" text="Vajar Kchorna " />
        <string id="str_tor_chaos_chaos_knight" text="Rycar Chaosu " />
        <string id="str_tor_beast_ungor" text="Niaroch " />
        <string id="str_tor_beast_shielded_ungor" text="Niaroch-Ščytanos " />
        <string id="str_tor_beast_ungor_raider" text="Niaroch-Nalotnik " />
        <string id="str_tor_beast_ungor_chief" text="Niaroch-Pravadyr " />
        <string id="str_tor_dog_braganza_01" text="Abłožnik-Arbaletnik " />
        <string id="str_tor_dog_braganza_02" text="Abłožnik-Arbalest " />
        <string id="str_tor_dog_braganza_03" text="Abłožnik Brahanzy " />
        <string id="str_tor_dog_cursed_company_01" text="Zaniavoleny Vajar " />
        <string id="str_tor_dog_cursed_company_02" text="Praklaty Vajar " />
        <string id="str_tor_dog_cursed_company_03" text="Praklaty Kampańjon " />
        <string id="str_tor_dog_leopard_01" text="Leapard-Najmit " />
        <string id="str_tor_dog_leopard_02" text="Leapard-Pikinior " />
        <string id="str_tor_dog_leopard_03" text="Leapard-Pikinior Leapolda " />
        <string id="str_tor_dog_voland_01" text="Konny Vinejtar-Najmit " />
        <string id="str_tor_dog_voland_02" text="Vinejtar-Kondaćjera " />
        <string id="str_tor_dog_voland_03" text="Vinejtar Vołanda " />
        <string id="str_tor_dog_muktar_01" text="Arabski Najmit-Końnik " />
        <string id="str_tor_dog_muktar_02" text="Arabski Pustelny Destryjer " />
        <string id="str_tor_dog_muktar_03" text="Pustelny Pios Al-Muktara " />
        <string id="str_tor_dog_miragliano_01" text="Arbaletnik Miraljana " />
        <string id="str_tor_dog_miragliano_02" text="Arbiełast Miraljana " />
        <string id="str_tor_dog_miragliano_03" text="Snajpier Miraljana " />
        <string id="str_tor_dog_ricco_01" text="Rymanski Patryjot " />
        <string id="str_tor_dog_ricco_02" text="Rymanski Pikinior " />
        <string id="str_tor_dog_ricco_03" text="Respublikanski Vartaŭnik Rykka " />
        <string id="str_tor_merc_free_company_volunteer" text="Samaachvotnik Volnaj Kampanii " />
        <string id="str_tor_merc_free_company_scout" text="Vyviednik Volnaj Kampanii " />
        <string id="str_tor_merc_free_company_militiaman" text="Rušeniec Volnaj Kampanii " />
        <string id="str_tor_merc_free_company_bowman" text="Łučnik Volnaj Kampanii " />
        <string id="str_tor_merc_free_company_pistolier" text="Pistaljer Volnaj Kampanii " />
        <string id="str_tor_ror_kragsburg_retainer" text="Słužačy fon Kraksburha " />
        <string id="str_tor_ror_kragsburg_sergeant" text="Siaržant fon Kraksburha " />
        <string id="str_tor_ror_kragsburg_house_guard" text="Vartaŭnik Doma fon Kraksburh " />
        <string id="str_tor_ror_kragsburg_personal_guard" text="Asabisty Vartaŭnik fon Kraksburha " />
        <string id="str_tor_ror_stir_river_scout" text="Vyviednik Raki Šcir " />
        <string id="str_tor_ror_stir_river_patrolman" text="Patrulny Raki Šcir " />
        <string id="str_tor_ror_stir_river_patrol_guardsman" text="Patrulny-Vartaŭnik Raki Šcir " />
        <string id="str_tor_ror_stir_river_patrol_nimrod" text="Patrulny Nimroda Raki Šcir " />
        <string id="str_tor_ror_blazing_sun_initiate" text="Inicyjavany Pałymianaha Sonca " />
        <string id="str_tor_ror_blazing_sun_knight" text="Rycar Pałymianaha Sonca " />
        <string id="str_tor_ror_blazing_sun_preceptor" text="Pryseptar Pałymianaha Sonca " />
        <string id="str_tor_ror_blazing_sun_demigryph_knight" text="Rycar na Demihryfie Pałymianaha Sonca " />
        <string id="str_tor_ror_blazing_sun_innercircle" text="Rycar Unutranaha Koła Pałymianaha Sonca " />
        <string id="str_tor_ror_blazing_sun_demigryph_innercircle" text="Demihryf Unutranaha Koła Pałymianaha Sonca " />
        <string id="str_tor_ror_grundel_defender_troop" text="Žaŭnier-Abaronca Hrundela " />
        <string id="str_tor_ror_grundel_defender_stalwart" text=" Abaronca Štalvarta Hrundela " />
        <string id="str_tor_ror_grundel_defender_sergeant" text="Siaržant-Abaronca Hrundela " />
        <string id="str_tor_ror_grundel_defender_defender" text="Chrabry Abaronca Hrundela " />
        <string id="str_tor_ror_deathjack_longbowman" text="Dlinnałučnik Śmiarotnaha Džeka " />
        <string id="str_tor_ror_deathjack_marksman" text="Snajpier Śmiarotnaha Džeka " />
        <string id="str_tor_ror_deathjack_toxophilite" text="Strełafił Śmiarotnaha Džeka " />
        <string id="str_tor_ror_ward_of_taal" text="Padapiečny Taala " />
        <string id="str_tor_ror_hunter_of_taal" text="Palaŭničy Taala " />
        <string id="str_tor_ror_horned_hunter" text="Rahaty Palaŭničy " />
        <string id="str_tor_ror_longshank_initiate" text="Daŭhanohi Inicyjavany " />
        <string id="str_tor_ror_longshank_strider" text="Daŭhanohi Badziaha " />
        <string id="str_tor_ror_longshank_warden" text="Daŭhanohi Nahladnik " />
        <string id="str_tor_ror_longshank_ranger" text="Daŭhanohi Rejndžar " />
        <string id="str_tor_ror_griffon_initiate" text="Inicyjavany Hryfona " />
        <string id="str_tor_ror_griffon_knight" text="Rycar Hryfona " />
        <string id="str_tor_ror_griffon_preceptor_knight" text="Rycar-Pryseptar Hryfona " />
        <string id="str_tor_ror_griffon_innercircle_knight" text="Rycar Hryfona Unutranaha Koła " />
        <string id="str_tor_ror_griffon_demi_knight" text="Rycar Hryfona na Demihryfie " />
        <string id="str_tor_ror_griffon_demi_preceptor_knight" text="Rycar-Pryseptar Hryfona na Demihryfie " />
        <string id="str_tor_ror_son_of_altdorf" text="Syn Altdorfa " />
        <string id="str_tor_ror_altdorf_companyman" text="Kampańjon Altdorfa " />
        <string id="str_tor_ror_altdorf_company_sergeant" text="Siaržant Kampanii Altdorfa " />
        <string id="str_tor_ror_sternieste_skeleton" text="Kaściak Zamka Štarniste " />
        <string id="str_tor_ror_sternieste_grave_guard" text="Vartaŭnik Mahiłaŭ Zamka Štarniste " />
        <string id="str_tor_ror_sternieste_sternsmen" text="Štarnar " />
        <string id="str_tor_ror_sternieste_black_knight" text="Čorny Rycar Zamka Štarniste " />
        <string id="str_tor_ror_sternieste_reaver" text="Spustašalnik Viereka " />
        <string id="str_tor_ror_dragon_knight_initiate" text="Inicyjavany Kryvavaha Drakona " />
        <string id="str_tor_ror_dragon_knight" text="Rycar Kryvavaha Drakona " />
        <string id="str_tor_ror_dragon_templar" text="Tamplijer Kryvavaha Drakona " />
        <string id="str_tor_ror_konigstein_skeleton" text="Pieraślednik Konihštajna " />
        <string id="str_tor_ror_konigstein_swordsman" text="Pieraślednik-Miečnik Konihštajna " />
        <string id="str_tor_ror_konigstein_spearman" text="Pieraślednik-Kapijnik Konihštajna " />
        <string id="str_tor_chaos_cult_acolyte" text="Kultyst Chaosu " />
        <string id="str_tor_chaos_cult_darksoul" text="Ciomnaja Duša Chaosu " />
        <string id="str_tor_chaos_cult_magister" text="Pały Mahistar " />
        <string id="str_tor_cult_bw_expelled_magister" text="Vyhnany Mahistar " />
        <string id="str_tor_cult_bw_vengeful_cultist" text="Pomślivy Kultyst " />
        <string id="str_tor_cult_bw_sorcerer_broken_wheel" text="Viadźmar Złamanaha Koła " />
        <string id="str_tor_cult_coi_unlit_candle" text="Patuchłaja Śviečka " />
        <string id="str_tor_cult_coi_beacon" text="Majak " />
        <string id="str_tor_cult_coi_order_of_star_acolyte" text="Ordenavy Zornaha Akalita " />
        <string id="str_tor_cult_fsf_puer_ulceris" text="Smurodzi Jaźvis " />
        <string id="str_tor_cult_fsf_ulcus_frater" text="Bratar Jazvus " />
        <string id="str_tor_cult_fsf_ulcerator" text="Jazvatar " />
        <string id="str_tor_roaming_undead_skeleton" text="Vałacužny Niamiortvy " />
        <string id="str_tor_roaming_undead_warrior" text="Vałacužny Niamiortvy Vajar " />
        <string id="str_tor_empire_outlaw" text="Impierski Złačynca " />
        <string id="str_tor_empire_outlaw_leader" text="Impierski Złačynca-Kapitan " />
        <string id="str_tor_empire_deserter" text="Dezertyr " />
        <string id="str_tor_empire_deserter_sergeant" text="Dezertyr-Siaržant " />
        <string id="str_tor_empire_deserter_scout" text="Dezertyr-Vyviednik " />
    </strings>
</base>