<?xml version="1.0" encoding="UTF-8"?>
<base xmlns:xsi="http://www.w3.org/2001/XMLSchema-instance" xmlns:xsd="http://www.w3.org/2001/XMLSchema" type="string">
 <strings>
  <string id="reiko.elmp.port.1" text="Port Łondana"/>
  <string id="reiko.elmp.port.2" text="Port Piembroka"/>
  <string id="reiko.elmp.port.3" text="Port Hłazha"/>
  <string id="reiko.elmp.port.4" text="Port Dublina"/>
  <string id="reiko.elmp.port.5" text="Port Paryža"/>
  <string id="reiko.elmp.port.6" text="Port Kaljary"/>
  <string id="reiko.elmp.port.7" text="Port Bierhiena"/>
  <string id="reiko.elmp.port.8" text="Port Tunisa"/>
  <string id="reiko.elmp.port.9" text="Port Ałžyra"/>
  <string id="reiko.elmp.port.10" text="Port Rabata"/>
  <string id="reiko.elmp.port.11" text="Port Hdańska"/>
  <string id="reiko.elmp.port.12" text="Port Hamburha"/>
  <string id="reiko.elmp.port.13" text="Port Ankony"/>
  <string id="reiko.elmp.port.14" text="Port Vieniecyi"/>
  <string id="reiko.elmp.port.15" text="Port Palerma"/>
  <string id="reiko.elmp.port.16" text="Port Nieapala"/>
  <string id="reiko.elmp.port.17" text="Port Hienui"/>
  <string id="reiko.elmp.port.18" text="Port Valensii"/>
  <string id="reiko.elmp.port.19" text="Port Lisabona"/>
  <string id="reiko.elmp.port.20" text="Port Sievilli"/>
  <string id="reiko.elmp.port.21" text="Port Barsiełony"/>
  <string id="reiko.elmp.port.22" text="Port Sanćjaha"/>
  <string id="reiko.elmp.port.23" text="Port Osła"/>
  <string id="reiko.elmp.port.24" text="Port Hiotebarha"/>
  <string id="reiko.elmp.port.25" text="Port Stakholma"/>
  <string id="reiko.elmp.port.26" text="Port Sundsvala"/>
  <string id="reiko.elmp.port.27" text="Port Kapienhahiena"/>
  <string id="reiko.elmp.port.28" text="Port Bardo"/>
  <string id="reiko.elmp.port.29" text="Port Nanta"/>
  <string id="reiko.elmp.port.30" text="Port Arleana"/>
  <string id="reiko.elmp.port.31" text="Port Marsela"/>
  <string id="reiko.elmp.port.32" text="Port Al-Iskandaryi"/>
  <string id="reiko.elmp.port.33" text="Port Al-Kachiry"/>
  <string id="reiko.elmp.port.34" text="Port Aśjuta"/>
  <string id="reiko.elmp.port.35" text="Port Binhazi"/>
  <string id="reiko.elmp.port.36" text="Port Tesałoniki"/>
  <string id="reiko.elmp.port.37" text="Port Afinaŭ"/>
  <string id="reiko.elmp.port.38" text="Port Iźmira"/>
  <string id="reiko.elmp.port.39" text="Port Kanstancinopala"/>
  <string id="reiko.elmp.port.40" text="Port Kaciubiejeva"/>
  <string id="reiko.elmp.port.41" text="Port Kierčy"/>
  <string id="reiko.elmp.port.42" text="Port Dzierbienta"/>
  <string id="reiko.elmp.port.43" text="Port Jalca"/>
  <string id="reiko.elmp.port.44" text="Port Kazani"/>
 </strings>
</base>