<?xml version="1.0" encoding="UTF-8"?>
<base xmlns:xsi="http://www.w3.org/2001/XMLSchema-instance" xmlns:xsd="http://www.w3.org/2001/XMLSchema" type="string">
 <strings>
  <string id="VPis3atP" text="Tetsojin Mercenaries Leader"/>
  <string id="umbrawar" text="Umbra Consul"/>
  <string id="hororec" text="Horosha Recruit"/>
  <string id="horowar" text="Horosha Warrior"/>
  <string id="horovet" text="Horosha Veteran Warrior"/>
  <string id="horoni" text="Horosha Oni"/>
  <string id="umbra" text="of the Umbra"/>
  <string id="horosha" text="of the Horosha"/>
 </strings>
</base>
