<?xml version="1.0" encoding="utf-8"?>
<base xmlns:xsi="http://www.w3.org/2001/XMLSchema-instance" xmlns:xsd="http://www.w3.org/2001/XMLSchema" type="string">
  <tags>
    <tag language="Русский" />
  </tags>
  <strings>
    <string id="074YAjOk" text="Вас исключили из-за неактивности" />
    <string id="1e12bdjj" text="Снимок экрана сохранен в папке {PATH}" />
    <string id="2SEofGth" text="Сменить команду" />
    <string id="3CsACce8" text="Выход" />
    <string id="4mMySbxI" text="Неизвестная ошибка" />
    <string id="79bODbwZ" text="Фоторежим уже используется." />
    <string id="a0IHtkoa" text="Вас исключили из игры" />
    <string id="aGGq9lJT" text="Сменить народность" />
    <string id="ajKnHI1s" text="Сделать снимок" />
    <string id="aKjpbRP5" text="Неизвестная причина" />
    <string id="aogZyZlR" text="Повторно использовать ликование/крик можно будет через {SECONDS} с." />
    <string id="asCeKZXx" text="Включить интерфейс битвы" />
    <string id="controllerDisconnectedDescriptionPS" text="Для продолжения подключите беспроводной контроллер заново" />
    <string id="controllerDisconnectedDescriptionXB" text="Для продолжения подключите геймпад заново" />
    <string id="controllerDisconnectedTitlePS" text="Беспроводной контроллер отключен" />
    <string id="controllerDisconnectedTitleXB" text="Геймпад отключен" />
    <string id="dismissnotification" text="Пропустить" />
    <string id="EzeFJo65" text="Вы были отключены от сервера!" />
    <string id="hvaDkG4w" text="Нажмите любую клавишу." />
    <string id="HzWaGn3y" text="Не все игроки запустили игру с античитом" />
    <string id="ImQnhIQ5" text="Фоторежим недоступен во время диалогов." />
    <string id="InGwtrWt" text="Выйти" />
    <string id="InUAmnX4" text="Вас исключили из-за нанесения урона соратникам" />
    <string id="ivKntfNA" text="Запрос на подключение уже отправлен, ожидается ответ сервера" />
    <string id="IzJ7f5SQ" text="Сервер заполнен" />
    <string id="JluTW3Qw" text="Игра окончена" />
    <string id="JQVixeQs" text="Не удалось подключиться к серверу игры" />
    <string id="KO2adj2I" text="Для присоединения к пользовательской игре нужно войти в лобби" />
    <string id="KQrpWV1n" text="Для присоединения к пользовательской игре вам нужно быть лидером отряда" />
    <string id="KRNdlbkq" text="Пользовательская игра завершается" />
    <string id="lxq6SaQn" text="Вы действительно хотите выйти?" />
    <string id="Mm1Kb1bS" text="Неправильный пароль" />
    <string id="mO9bh5sy" text="Не удалось войти в пользовательскую игру" />
    <string id="n4UUrd1p" text="Уже используется" />
    <string id="NqarFr4P" text="Параметры" />
    <string id="O1bGoaE8" text="Сервер не отвечает. Пожалуйста, попробуйте еще раз." />
    <string id="OhF7NqSb" text="Вас заблокировали голосованием" />
    <string id="RamV6yLM" text="Выход в главное меню" />
    <string id="RGzyUTzm" text="Построение подразделения изменено на: {ARRANGEMENT_ORDER}" />
    <string id="srAJw3Tg" text="Игрок заблокирован на сервере" />
    <string id="T8IniCKU" text="Игровой сервер недоступен" />
    <string id="tKSxGy5p" text="Сервер не отвечает" />
    <string id="tlsmbvQX" text="Не все игроки готовы присоединиться" />
    <string id="TR1B2RWB" text="Вас исключил из игры античит" />
    <string id="VklN5Wm6" text="Фоторежим" />
    <string id="vkpMgobZ" text="Ошибка игрового сервера" />
    <string id="wbFB3N72" text="Вас исключили из игры голосованием" />
    <string id="wLpJEkKY" text="Сбой сервера битвы" />
    <string id="WvGviFgt" text="Истекло время подключения к серверу" />
    <string id="XzZFhRwr" text="Вернуться в игру" />
    <string id="yS7PvrTD" text="ОК" />
    <string id="Yza0JYJt" text="Сменить воина" />
  </strings>
</base>